protectwise/__init__.py
protectwise_lib-0.0.8.dist-info/LICENSE
protectwise_lib-0.0.8.dist-info/METADATA
protectwise_lib-0.0.8.dist-info/WHEEL
protectwise_lib-0.0.8.dist-info/top_level.txt
protectwise_lib-0.0.8.dist-info/RECORD
