Metadata-Version: 2.1
Name: protectwise-lib
Version: 0.0.8
Summary: A python Library for interacting with Protectwise API
Home-page: https://github.com/5A4B48/protectwise-lib
Author: 5A4B48
Author-email: pw@cybersecintel.ca
License: UNKNOWN
Platform: UNKNOWN
Classifier: Programming Language :: Python :: 3
Classifier: License :: OSI Approved :: BSD License
Classifier: Operating System :: OS Independent
Requires-Python: >=3.1
Requires-Dist: requests
